almanac/__init__.py
almanac/__main__.py
almanac/version.py
almanac/arguments/__init__.py
almanac/arguments/argument_base.py
almanac/arguments/frozen_argument.py
almanac/arguments/mutable_argument.py
almanac/commands/__init__.py
almanac/commands/command_base.py
almanac/commands/frozen_command.py
almanac/commands/mutable_command.py
almanac/completion/__init__.py
almanac/completion/completion_utils.py
almanac/completion/page_path_completer.py
almanac/completion/word_completer.py
almanac/constants/__init__.py
almanac/constants/defaults.py
almanac/constants/exit_codes.py
almanac/context/__init__.py
almanac/context/context.py
almanac/core/__init__.py
almanac/core/application.py
almanac/core/command_completer.py
almanac/core/command_engine.py
almanac/core/decorators.py
almanac/errors/__init__.py
almanac/errors/almanac_error.py
almanac/errors/argument_errors/__init__.py
almanac/errors/argument_errors/argument_name_collision_error.py
almanac/errors/argument_errors/base_argument_error.py
almanac/errors/argument_errors/invalid_argument_name_error.py
almanac/errors/argument_errors/missing_arguments_error.py
almanac/errors/argument_errors/no_such_argument_error.py
almanac/errors/argument_errors/too_many_positional_arguments_error.py
almanac/errors/argument_errors/unknown_argument_binding_error.py
almanac/errors/command_errors/__init__.py
almanac/errors/command_errors/base_command_error.py
almanac/errors/command_errors/command_name_collision_error.py
almanac/errors/command_errors/command_registration_error.py
almanac/errors/command_errors/no_such_command_error.py
almanac/errors/configuration_errors/__init__.py
almanac/errors/configuration_errors/base_configuration_error.py
almanac/errors/configuration_errors/conflicting_exception_callbacks_error.py
almanac/errors/configuration_errors/conflicting_promoter_types_error.py
almanac/errors/configuration_errors/invalid_callback_type_error.py
almanac/errors/configuration_errors/missing_required_parameter_error.py
almanac-0.1.0.dist-info/LICENSE.txt
almanac-0.1.0.dist-info/METADATA
almanac-0.1.0.dist-info/WHEEL
almanac-0.1.0.dist-info/top_level.txt
almanac-0.1.0.dist-info/RECORD
