Metadata-Version: 2.1
Name: almanac
Version: 0.1.0
Summary: a framework for interactive, page-based console applications
Home-page: https://almanac.brianwel.ch
Author: Brian Welch
Author-email: welch18@vt.edu
License: MIT
Platform: UNKNOWN
Classifier: License :: OSI Approved :: MIT License
Classifier: Development Status :: 4 - Beta
Classifier: Environment :: Console
Classifier: Framework :: AsyncIO
Classifier: Intended Audience :: Developers
Classifier: License :: OSI Approved :: MIT License
Classifier: Operating System :: OS Independent
Classifier: Programming Language :: Python :: 3.8
Classifier: Programming Language :: Python :: 3.9
Classifier: Typing :: Typed
Requires-Dist: munch (==2.5.0)
Requires-Dist: prompt-toolkit (==3.0.5)
Requires-Dist: Pygments (==2.6.1)
Requires-Dist: pyparsing (==2.4.7)
Requires-Dist: typing-inspect (==0.6.0)
Requires-Dist: wcwidth (==0.2.5)
